playdate_midi_converter/MIDI to JSON.py
playdate_midi_converter/__init__.py
playdate_midi_converter/__version__.py
playdate_midi_converter/config.py
playdate_midi_converter/convert.py
playdate_midi_converter/encode.py
playdate_midi_converter/json.py
playdate_midi_converter/midi.py
playdate_midi_converter/song.py
playdate_midi_converter/strenum.py
playdate_midi_converter/JSON_Elements/JSON_Notes.py
playdate_midi_converter/JSON_Elements/JSON_Songs.py
playdate_midi_converter/JSON_Elements/__init__.py
playdate_midi_converter/MIDI_Elements/MIDI_Track.py
playdate_midi_converter/MIDI_Elements/__init__.py
playdate_midi_converter/entry_points/__init__.py
playdate_midi_converter/entry_points/console_scripts/__init__.py
playdate_midi_converter/entry_points/console_scripts/playdate_pulp_midi.py
playdate_midi_converter/ui/__init__.py
playdate_midi_converter/ui/input.py
playdate_midi_converter/ui/cli/__init__.py
playdate_midi_converter/ui/cli/channel_mapping.py
playdate_midi_converter/ui/common/__init__.py
playdate_midi_converter/ui/common/channel_mapping.py
playdate_midi_converter-0.0.2.dist-info/LICENSE.txt
playdate_midi_converter-0.0.2.dist-info/METADATA
playdate_midi_converter-0.0.2.dist-info/WHEEL
playdate_midi_converter-0.0.2.dist-info/entry_points.txt
playdate_midi_converter-0.0.2.dist-info/top_level.txt
playdate_midi_converter-0.0.2.dist-info/RECORD
